MANIFEST.in
README.rst
requirements.txt
setup.py
twitterscraper/__init__.py
twitterscraper/logging.py
twitterscraper/main.py
twitterscraper/query.py
twitterscraper/tweet.py
twitterscraper.egg-info/PKG-INFO
twitterscraper.egg-info/SOURCES.txt
twitterscraper.egg-info/dependency_links.txt
twitterscraper.egg-info/entry_points.txt
twitterscraper.egg-info/requires.txt
twitterscraper.egg-info/top_level.txt