Metadata-Version: 1.0
Name: twitterscraper
Version: 0.7.1
Summary: Tool for scraping Tweets
Home-page: https://github.com/taspinar/twitterscraper
Author: ['Ahmet Taspinar', 'Lasse Schuirmann']
Author-email: taspinar@gmail.com
License: MIT
Platform: UNKNOWN
